mediaSecure/__init__.py
mediaSecure/encodeB64.py
mediaSecure/test_encodeB64.py
MediaSecure-1.0.0.dist-info/METADATA
MediaSecure-1.0.0.dist-info/WHEEL
MediaSecure-1.0.0.dist-info/top_level.txt
MediaSecure-1.0.0.dist-info/RECORD
