Metadata-Version: 2.1
Name: MediaSecure
Version: 1.0.0
Summary: Project Description: MediaEncryptor
Author-email: Abdel-Rahman Saied <abdelrahmansaied080@gmail.com>
Project-URL: Homepage, https://github.com/Abdel-RahmanSaied/mediaSecure.git
Classifier: Programming Language :: Python :: 3
Classifier: License :: OSI Approved :: MIT License
Classifier: Operating System :: OS Independent
Requires-Python: >=3.7
